ttcv/__init__.cpython-36m-x86_64-linux-gnu.so
ttcv/import_basic_utils.cpython-36m-x86_64-linux-gnu.so
ttcv/basic/__init__.cpython-36m-x86_64-linux-gnu.so
ttcv/basic/basic_gui.cpython-36m-x86_64-linux-gnu.so
ttcv/basic/basic_objects.cpython-36m-x86_64-linux-gnu.so
ttcv/basic/basic_onmouse.cpython-36m-x86_64-linux-gnu.so
ttcv/basic/basic_sequence.cpython-36m-x86_64-linux-gnu.so
ttcv/basic/basic_tcp_connect.cpython-36m-x86_64-linux-gnu.so
ttcv/configs/__init__.cpython-36m-x86_64-linux-gnu.so
ttcv/configs/default_config.cpython-36m-x86_64-linux-gnu.so
ttcv/dataset/__init__.cpython-36m-x86_64-linux-gnu.so
ttcv/dataset/polygon.cpython-36m-x86_64-linux-gnu.so
ttcv/robot/__init__.cpython-36m-x86_64-linux-gnu.so
ttcv/robot/hcr_manipulation.cpython-36m-x86_64-linux-gnu.so
ttcv/samples/__init__.cpython-36m-x86_64-linux-gnu.so
ttcv/samples/demo_client_gui.cpython-36m-x86_64-linux-gnu.so
ttcv/samples/demo_image_process.cpython-36m-x86_64-linux-gnu.so
ttcv/samples/run_auto_detect_realsense.cpython-36m-x86_64-linux-gnu.so
ttcv/samples/select_sample.cpython-36m-x86_64-linux-gnu.so
ttcv/sensor/__init__.cpython-36m-x86_64-linux-gnu.so
ttcv/sensor/helios.cpython-36m-x86_64-linux-gnu.so
ttcv/sensor/kinect_azure.cpython-36m-x86_64-linux-gnu.so
ttcv/sensor/realsense_sensor.cpython-36m-x86_64-linux-gnu.so
ttcv/sensor/sensor.cpython-36m-x86_64-linux-gnu.so
ttcv/sensor/sensor_v2.cpython-36m-x86_64-linux-gnu.so
ttcv/utils/__init__.cpython-36m-x86_64-linux-gnu.so
ttcv/utils/array_utils.cpython-36m-x86_64-linux-gnu.so
ttcv/utils/data_utilts.cpython-36m-x86_64-linux-gnu.so
ttcv/utils/grasp_utils.cpython-36m-x86_64-linux-gnu.so
ttcv/utils/gui_utils.cpython-36m-x86_64-linux-gnu.so
ttcv/utils/makedb_utilts.cpython-36m-x86_64-linux-gnu.so
ttcv/utils/proc_utils.cpython-36m-x86_64-linux-gnu.so
ttcv/utils/rgbd_utils.cpython-36m-x86_64-linux-gnu.so
ttcv/utils/rgbd_utils_v2.cpython-36m-x86_64-linux-gnu.so
ttcv-1.0.14.dist-info/LICENSE
ttcv-1.0.14.dist-info/METADATA
ttcv-1.0.14.dist-info/WHEEL
ttcv-1.0.14.dist-info/entry_points.txt
ttcv-1.0.14.dist-info/top_level.txt
ttcv-1.0.14.dist-info/RECORD
