Metadata-Version: 2.1
Name: ttcv
Version: 1.0.14
Summary: An AI picking package
Home-page: https://github.com/mtbui2010
Author: Trung M. Bui
Author-email: bmtrungvp@gmail.com
License: MIT
Keywords: AI,VISION,UTILITY
Platform: UNKNOWN
Classifier: Programming Language :: Python :: 3
Classifier: License :: OSI Approved :: MIT License
Classifier: Operating System :: OS Independent
Requires-Python: >=3.6
Requires-Dist: numpy
Requires-Dist: opencv-python
Requires-Dist: scipy
Requires-Dist: matplotlib
